jasn1/__init__.py
jasn1/parse.py
jasn1/asn1/__init__.py
jasn1/asn1/types.py
jasn1/asn1/types__deprecated.py
jasn1/bidict/__init__.py
jasn1/ldap/__init__.py
jasn1/ldap/types.py
jasn1/ldap/types__deprecated.py
jasn1/snmp/__init__.py
jasn1/snmp/types.py
jasn1-0.0.2.dist-info/METADATA
jasn1-0.0.2.dist-info/WHEEL
jasn1-0.0.2.dist-info/top_level.txt
jasn1-0.0.2.dist-info/RECORD
