Metadata-Version: 2.1
Name: jasn1
Version: 0.0.2
Summary: Parsing ASN.1 data to JSON and vice-versa
Author: Matthew Laurence William Graham
Author-email: matthew.graham@skyhyve.com.au
License: UNKNOWN
Platform: UNKNOWN
